{
  "type": "File",
  "start": 0,
  "end": 165,
  "loc": {
    "start": {
      "line": 1,
      "column": 0
    },
    "end": {
      "line": 6,
      "column": 0
    }
  },
  "program": {
    "type": "Program",
    "start": 0,
    "end": 165,
    "loc": {
      "start": {
        "line": 1,
        "column": 0
      },
      "end": {
        "line": 6,
        "column": 0
      }
    },
    "sourceType": "module",
    "body": [
      {
        "type": "ImportDeclaration",
        "start": 0,
        "end": 50,
        "loc": {
          "start": {
            "line": 1,
            "column": 0
          },
          "end": {
            "line": 1,
            "column": 50
          }
        },
        "specifiers": [
          {
            "type": "ImportSpecifier",
            "start": 9,
            "end": 19,
            "loc": {
              "start": {
                "line": 1,
                "column": 9
              },
              "end": {
                "line": 1,
                "column": 19
              }
            },
            "imported": {
              "type": "Identifier",
              "start": 9,
              "end": 19,
              "loc": {
                "start": {
                  "line": 1,
                  "column": 9
                },
                "end": {
                  "line": 1,
                  "column": 19
                },
                "identifierName": "ARRAY_TYPE"
              },
              "name": "ARRAY_TYPE"
            },
            "local": {
              "type": "Identifier",
              "start": 9,
              "end": 19,
              "loc": {
                "start": {
                  "line": 1,
                  "column": 9
                },
                "end": {
                  "line": 1,
                  "column": 19
                },
                "identifierName": "ARRAY_TYPE"
              },
              "name": "ARRAY_TYPE"
            }
          },
          {
            "type": "ImportSpecifier",
            "start": 21,
            "end": 33,
            "loc": {
              "start": {
                "line": 1,
                "column": 21
              },
              "end": {
                "line": 1,
                "column": 33
              }
            },
            "imported": {
              "type": "Identifier",
              "start": 21,
              "end": 33,
              "loc": {
                "start": {
                  "line": 1,
                  "column": 21
                },
                "end": {
                  "line": 1,
                  "column": 33
                },
                "identifierName": "getCSSStyles"
              },
              "name": "getCSSStyles"
            },
            "local": {
              "type": "Identifier",
              "start": 21,
              "end": 33,
              "loc": {
                "start": {
                  "line": 1,
                  "column": 21
                },
                "end": {
                  "line": 1,
                  "column": 33
                },
                "identifierName": "getCSSStyles"
              },
              "name": "getCSSStyles"
            }
          }
        ],
        "source": {
          "type": "StringLiteral",
          "start": 41,
          "end": 49,
          "loc": {
            "start": {
              "line": 1,
              "column": 41
            },
            "end": {
              "line": 1,
              "column": 49
            }
          },
          "extra": {
            "rawValue": "./util",
            "raw": "'./util'"
          },
          "value": "./util"
        }
      },
      {
        "type": "ImportDeclaration",
        "start": 51,
        "end": 82,
        "loc": {
          "start": {
            "line": 2,
            "column": 0
          },
          "end": {
            "line": 2,
            "column": 31
          }
        },
        "specifiers": [
          {
            "type": "ImportNamespaceSpecifier",
            "start": 58,
            "end": 67,
            "loc": {
              "start": {
                "line": 2,
                "column": 7
              },
              "end": {
                "line": 2,
                "column": 16
              }
            },
            "local": {
              "type": "Identifier",
              "start": 63,
              "end": 67,
              "loc": {
                "start": {
                  "line": 2,
                  "column": 12
                },
                "end": {
                  "line": 2,
                  "column": 16
                },
                "identifierName": "Vec3"
              },
              "name": "Vec3"
            }
          }
        ],
        "source": {
          "type": "StringLiteral",
          "start": 73,
          "end": 81,
          "loc": {
            "start": {
              "line": 2,
              "column": 22
            },
            "end": {
              "line": 2,
              "column": 30
            }
          },
          "extra": {
            "rawValue": "./vec3",
            "raw": "'./vec3'"
          },
          "value": "./vec3"
        }
      },
      {
        "type": "ImportDeclaration",
        "start": 83,
        "end": 114,
        "loc": {
          "start": {
            "line": 3,
            "column": 0
          },
          "end": {
            "line": 3,
            "column": 31
          }
        },
        "specifiers": [
          {
            "type": "ImportNamespaceSpecifier",
            "start": 90,
            "end": 99,
            "loc": {
              "start": {
                "line": 3,
                "column": 7
              },
              "end": {
                "line": 3,
                "column": 16
              }
            },
            "local": {
              "type": "Identifier",
              "start": 95,
              "end": 99,
              "loc": {
                "start": {
                  "line": 3,
                  "column": 12
                },
                "end": {
                  "line": 3,
                  "column": 16
                },
                "identifierName": "Mat4"
              },
              "name": "Mat4"
            }
          }
        ],
        "source": {
          "type": "StringLiteral",
          "start": 105,
          "end": 113,
          "loc": {
            "start": {
              "line": 3,
              "column": 22
            },
            "end": {
              "line": 3,
              "column": 30
            }
          },
          "extra": {
            "rawValue": "./mat4",
            "raw": "'./mat4'"
          },
          "value": "./mat4"
        }
      },
      {
        "type": "ExportNamedDeclaration",
        "start": 116,
        "end": 164,
        "loc": {
          "start": {
            "line": 5,
            "column": 0
          },
          "end": {
            "line": 5,
            "column": 48
          }
        },
        "declaration": null,
        "specifiers": [
          {
            "type": "ExportSpecifier",
            "start": 125,
            "end": 135,
            "loc": {
              "start": {
                "line": 5,
                "column": 9
              },
              "end": {
                "line": 5,
                "column": 19
              }
            },
            "local": {
              "type": "Identifier",
              "start": 125,
              "end": 135,
              "loc": {
                "start": {
                  "line": 5,
                  "column": 9
                },
                "end": {
                  "line": 5,
                  "column": 19
                },
                "identifierName": "ARRAY_TYPE"
              },
              "name": "ARRAY_TYPE"
            },
            "exported": {
              "type": "Identifier",
              "start": 125,
              "end": 135,
              "loc": {
                "start": {
                  "line": 5,
                  "column": 9
                },
                "end": {
                  "line": 5,
                  "column": 19
                },
                "identifierName": "ARRAY_TYPE"
              },
              "name": "ARRAY_TYPE"
            }
          },
          {
            "type": "ExportSpecifier",
            "start": 137,
            "end": 149,
            "loc": {
              "start": {
                "line": 5,
                "column": 21
              },
              "end": {
                "line": 5,
                "column": 33
              }
            },
            "local": {
              "type": "Identifier",
              "start": 137,
              "end": 149,
              "loc": {
                "start": {
                  "line": 5,
                  "column": 21
                },
                "end": {
                  "line": 5,
                  "column": 33
                },
                "identifierName": "getCSSStyles"
              },
              "name": "getCSSStyles"
            },
            "exported": {
              "type": "Identifier",
              "start": 137,
              "end": 149,
              "loc": {
                "start": {
                  "line": 5,
                  "column": 21
                },
                "end": {
                  "line": 5,
                  "column": 33
                },
                "identifierName": "getCSSStyles"
              },
              "name": "getCSSStyles"
            }
          },
          {
            "type": "ExportSpecifier",
            "start": 151,
            "end": 155,
            "loc": {
              "start": {
                "line": 5,
                "column": 35
              },
              "end": {
                "line": 5,
                "column": 39
              }
            },
            "local": {
              "type": "Identifier",
              "start": 151,
              "end": 155,
              "loc": {
                "start": {
                  "line": 5,
                  "column": 35
                },
                "end": {
                  "line": 5,
                  "column": 39
                },
                "identifierName": "Vec3"
              },
              "name": "Vec3"
            },
            "exported": {
              "type": "Identifier",
              "start": 151,
              "end": 155,
              "loc": {
                "start": {
                  "line": 5,
                  "column": 35
                },
                "end": {
                  "line": 5,
                  "column": 39
                },
                "identifierName": "Vec3"
              },
              "name": "Vec3"
            }
          },
          {
            "type": "ExportSpecifier",
            "start": 157,
            "end": 161,
            "loc": {
              "start": {
                "line": 5,
                "column": 41
              },
              "end": {
                "line": 5,
                "column": 45
              }
            },
            "local": {
              "type": "Identifier",
              "start": 157,
              "end": 161,
              "loc": {
                "start": {
                  "line": 5,
                  "column": 41
                },
                "end": {
                  "line": 5,
                  "column": 45
                },
                "identifierName": "Mat4"
              },
              "name": "Mat4"
            },
            "exported": {
              "type": "Identifier",
              "start": 157,
              "end": 161,
              "loc": {
                "start": {
                  "line": 5,
                  "column": 41
                },
                "end": {
                  "line": 5,
                  "column": 45
                },
                "identifierName": "Mat4"
              },
              "name": "Mat4"
            }
          }
        ],
        "source": null
      }
    ],
    "directives": []
  },
  "comments": [],
  "tokens": [
    {
      "type": {
        "label": "import",
        "keyword": "import",
        "beforeExpr": false,
        "startsExpr": true,
        "rightAssociative": false,
        "isLoop": false,
        "isAssign": false,
        "prefix": false,
        "postfix": false,
        "binop": null,
        "updateContext": null
      },
      "value": "import",
      "start": 0,
      "end": 6,
      "loc": {
        "start": {
          "line": 1,
          "column": 0
        },
        "end": {
          "line": 1,
          "column": 6
        }
      }
    },
    {
      "type": {
        "label": "{",
        "beforeExpr": true,
        "startsExpr": true,
        "rightAssociative": false,
        "isLoop": false,
        "isAssign": false,
        "prefix": false,
        "postfix": false,
        "binop": null
      },
      "start": 7,
      "end": 8,
      "loc": {
        "start": {
          "line": 1,
          "column": 7
        },
        "end": {
          "line": 1,
          "column": 8
        }
      }
    },
    {
      "type": {
        "label": "name",
        "beforeExpr": false,
        "startsExpr": true,
        "rightAssociative": false,
        "isLoop": false,
        "isAssign": false,
        "prefix": false,
        "postfix": false,
        "binop": null
      },
      "value": "ARRAY_TYPE",
      "start": 9,
      "end": 19,
      "loc": {
        "start": {
          "line": 1,
          "column": 9
        },
        "end": {
          "line": 1,
          "column": 19
        }
      }
    },
    {
      "type": {
        "label": ",",
        "beforeExpr": true,
        "startsExpr": false,
        "rightAssociative": false,
        "isLoop": false,
        "isAssign": false,
        "prefix": false,
        "postfix": false,
        "binop": null,
        "updateContext": null
      },
      "start": 19,
      "end": 20,
      "loc": {
        "start": {
          "line": 1,
          "column": 19
        },
        "end": {
          "line": 1,
          "column": 20
        }
      }
    },
    {
      "type": {
        "label": "name",
        "beforeExpr": false,
        "startsExpr": true,
        "rightAssociative": false,
        "isLoop": false,
        "isAssign": false,
        "prefix": false,
        "postfix": false,
        "binop": null
      },
      "value": "getCSSStyles",
      "start": 21,
      "end": 33,
      "loc": {
        "start": {
          "line": 1,
          "column": 21
        },
        "end": {
          "line": 1,
          "column": 33
        }
      }
    },
    {
      "type": {
        "label": "}",
        "beforeExpr": false,
        "startsExpr": false,
        "rightAssociative": false,
        "isLoop": false,
        "isAssign": false,
        "prefix": false,
        "postfix": false,
        "binop": null
      },
      "start": 34,
      "end": 35,
      "loc": {
        "start": {
          "line": 1,
          "column": 34
        },
        "end": {
          "line": 1,
          "column": 35
        }
      }
    },
    {
      "type": {
        "label": "name",
        "beforeExpr": false,
        "startsExpr": true,
        "rightAssociative": false,
        "isLoop": false,
        "isAssign": false,
        "prefix": false,
        "postfix": false,
        "binop": null
      },
      "value": "from",
      "start": 36,
      "end": 40,
      "loc": {
        "start": {
          "line": 1,
          "column": 36
        },
        "end": {
          "line": 1,
          "column": 40
        }
      }
    },
    {
      "type": {
        "label": "string",
        "beforeExpr": false,
        "startsExpr": true,
        "rightAssociative": false,
        "isLoop": false,
        "isAssign": false,
        "prefix": false,
        "postfix": false,
        "binop": null,
        "updateContext": null
      },
      "value": "./util",
      "start": 41,
      "end": 49,
      "loc": {
        "start": {
          "line": 1,
          "column": 41
        },
        "end": {
          "line": 1,
          "column": 49
        }
      }
    },
    {
      "type": {
        "label": ";",
        "beforeExpr": true,
        "startsExpr": false,
        "rightAssociative": false,
        "isLoop": false,
        "isAssign": false,
        "prefix": false,
        "postfix": false,
        "binop": null,
        "updateContext": null
      },
      "start": 49,
      "end": 50,
      "loc": {
        "start": {
          "line": 1,
          "column": 49
        },
        "end": {
          "line": 1,
          "column": 50
        }
      }
    },
    {
      "type": {
        "label": "import",
        "keyword": "import",
        "beforeExpr": false,
        "startsExpr": true,
        "rightAssociative": false,
        "isLoop": false,
        "isAssign": false,
        "prefix": false,
        "postfix": false,
        "binop": null,
        "updateContext": null
      },
      "value": "import",
      "start": 51,
      "end": 57,
      "loc": {
        "start": {
          "line": 2,
          "column": 0
        },
        "end": {
          "line": 2,
          "column": 6
        }
      }
    },
    {
      "type": {
        "label": "*",
        "beforeExpr": true,
        "startsExpr": false,
        "rightAssociative": false,
        "isLoop": false,
        "isAssign": false,
        "prefix": false,
        "postfix": false,
        "binop": 10,
        "updateContext": null
      },
      "value": "*",
      "start": 58,
      "end": 59,
      "loc": {
        "start": {
          "line": 2,
          "column": 7
        },
        "end": {
          "line": 2,
          "column": 8
        }
      }
    },
    {
      "type": {
        "label": "name",
        "beforeExpr": false,
        "startsExpr": true,
        "rightAssociative": false,
        "isLoop": false,
        "isAssign": false,
        "prefix": false,
        "postfix": false,
        "binop": null
      },
      "value": "as",
      "start": 60,
      "end": 62,
      "loc": {
        "start": {
          "line": 2,
          "column": 9
        },
        "end": {
          "line": 2,
          "column": 11
        }
      }
    },
    {
      "type": {
        "label": "name",
        "beforeExpr": false,
        "startsExpr": true,
        "rightAssociative": false,
        "isLoop": false,
        "isAssign": false,
        "prefix": false,
        "postfix": false,
        "binop": null
      },
      "value": "Vec3",
      "start": 63,
      "end": 67,
      "loc": {
        "start": {
          "line": 2,
          "column": 12
        },
        "end": {
          "line": 2,
          "column": 16
        }
      }
    },
    {
      "type": {
        "label": "name",
        "beforeExpr": false,
        "startsExpr": true,
        "rightAssociative": false,
        "isLoop": false,
        "isAssign": false,
        "prefix": false,
        "postfix": false,
        "binop": null
      },
      "value": "from",
      "start": 68,
      "end": 72,
      "loc": {
        "start": {
          "line": 2,
          "column": 17
        },
        "end": {
          "line": 2,
          "column": 21
        }
      }
    },
    {
      "type": {
        "label": "string",
        "beforeExpr": false,
        "startsExpr": true,
        "rightAssociative": false,
        "isLoop": false,
        "isAssign": false,
        "prefix": false,
        "postfix": false,
        "binop": null,
        "updateContext": null
      },
      "value": "./vec3",
      "start": 73,
      "end": 81,
      "loc": {
        "start": {
          "line": 2,
          "column": 22
        },
        "end": {
          "line": 2,
          "column": 30
        }
      }
    },
    {
      "type": {
        "label": ";",
        "beforeExpr": true,
        "startsExpr": false,
        "rightAssociative": false,
        "isLoop": false,
        "isAssign": false,
        "prefix": false,
        "postfix": false,
        "binop": null,
        "updateContext": null
      },
      "start": 81,
      "end": 82,
      "loc": {
        "start": {
          "line": 2,
          "column": 30
        },
        "end": {
          "line": 2,
          "column": 31
        }
      }
    },
    {
      "type": {
        "label": "import",
        "keyword": "import",
        "beforeExpr": false,
        "startsExpr": true,
        "rightAssociative": false,
        "isLoop": false,
        "isAssign": false,
        "prefix": false,
        "postfix": false,
        "binop": null,
        "updateContext": null
      },
      "value": "import",
      "start": 83,
      "end": 89,
      "loc": {
        "start": {
          "line": 3,
          "column": 0
        },
        "end": {
          "line": 3,
          "column": 6
        }
      }
    },
    {
      "type": {
        "label": "*",
        "beforeExpr": true,
        "startsExpr": false,
        "rightAssociative": false,
        "isLoop": false,
        "isAssign": false,
        "prefix": false,
        "postfix": false,
        "binop": 10,
        "updateContext": null
      },
      "value": "*",
      "start": 90,
      "end": 91,
      "loc": {
        "start": {
          "line": 3,
          "column": 7
        },
        "end": {
          "line": 3,
          "column": 8
        }
      }
    },
    {
      "type": {
        "label": "name",
        "beforeExpr": false,
        "startsExpr": true,
        "rightAssociative": false,
        "isLoop": false,
        "isAssign": false,
        "prefix": false,
        "postfix": false,
        "binop": null
      },
      "value": "as",
      "start": 92,
      "end": 94,
      "loc": {
        "start": {
          "line": 3,
          "column": 9
        },
        "end": {
          "line": 3,
          "column": 11
        }
      }
    },
    {
      "type": {
        "label": "name",
        "beforeExpr": false,
        "startsExpr": true,
        "rightAssociative": false,
        "isLoop": false,
        "isAssign": false,
        "prefix": false,
        "postfix": false,
        "binop": null
      },
      "value": "Mat4",
      "start": 95,
      "end": 99,
      "loc": {
        "start": {
          "line": 3,
          "column": 12
        },
        "end": {
          "line": 3,
          "column": 16
        }
      }
    },
    {
      "type": {
        "label": "name",
        "beforeExpr": false,
        "startsExpr": true,
        "rightAssociative": false,
        "isLoop": false,
        "isAssign": false,
        "prefix": false,
        "postfix": false,
        "binop": null
      },
      "value": "from",
      "start": 100,
      "end": 104,
      "loc": {
        "start": {
          "line": 3,
          "column": 17
        },
        "end": {
          "line": 3,
          "column": 21
        }
      }
    },
    {
      "type": {
        "label": "string",
        "beforeExpr": false,
        "startsExpr": true,
        "rightAssociative": false,
        "isLoop": false,
        "isAssign": false,
        "prefix": false,
        "postfix": false,
        "binop": null,
        "updateContext": null
      },
      "value": "./mat4",
      "start": 105,
      "end": 113,
      "loc": {
        "start": {
          "line": 3,
          "column": 22
        },
        "end": {
          "line": 3,
          "column": 30
        }
      }
    },
    {
      "type": {
        "label": ";",
        "beforeExpr": true,
        "startsExpr": false,
        "rightAssociative": false,
        "isLoop": false,
        "isAssign": false,
        "prefix": false,
        "postfix": false,
        "binop": null,
        "updateContext": null
      },
      "start": 113,
      "end": 114,
      "loc": {
        "start": {
          "line": 3,
          "column": 30
        },
        "end": {
          "line": 3,
          "column": 31
        }
      }
    },
    {
      "type": {
        "label": "export",
        "keyword": "export",
        "beforeExpr": false,
        "startsExpr": false,
        "rightAssociative": false,
        "isLoop": false,
        "isAssign": false,
        "prefix": false,
        "postfix": false,
        "binop": null,
        "updateContext": null
      },
      "value": "export",
      "start": 116,
      "end": 122,
      "loc": {
        "start": {
          "line": 5,
          "column": 0
        },
        "end": {
          "line": 5,
          "column": 6
        }
      }
    },
    {
      "type": {
        "label": "{",
        "beforeExpr": true,
        "startsExpr": true,
        "rightAssociative": false,
        "isLoop": false,
        "isAssign": false,
        "prefix": false,
        "postfix": false,
        "binop": null
      },
      "start": 123,
      "end": 124,
      "loc": {
        "start": {
          "line": 5,
          "column": 7
        },
        "end": {
          "line": 5,
          "column": 8
        }
      }
    },
    {
      "type": {
        "label": "name",
        "beforeExpr": false,
        "startsExpr": true,
        "rightAssociative": false,
        "isLoop": false,
        "isAssign": false,
        "prefix": false,
        "postfix": false,
        "binop": null
      },
      "value": "ARRAY_TYPE",
      "start": 125,
      "end": 135,
      "loc": {
        "start": {
          "line": 5,
          "column": 9
        },
        "end": {
          "line": 5,
          "column": 19
        }
      }
    },
    {
      "type": {
        "label": ",",
        "beforeExpr": true,
        "startsExpr": false,
        "rightAssociative": false,
        "isLoop": false,
        "isAssign": false,
        "prefix": false,
        "postfix": false,
        "binop": null,
        "updateContext": null
      },
      "start": 135,
      "end": 136,
      "loc": {
        "start": {
          "line": 5,
          "column": 19
        },
        "end": {
          "line": 5,
          "column": 20
        }
      }
    },
    {
      "type": {
        "label": "name",
        "beforeExpr": false,
        "startsExpr": true,
        "rightAssociative": false,
        "isLoop": false,
        "isAssign": false,
        "prefix": false,
        "postfix": false,
        "binop": null
      },
      "value": "getCSSStyles",
      "start": 137,
      "end": 149,
      "loc": {
        "start": {
          "line": 5,
          "column": 21
        },
        "end": {
          "line": 5,
          "column": 33
        }
      }
    },
    {
      "type": {
        "label": ",",
        "beforeExpr": true,
        "startsExpr": false,
        "rightAssociative": false,
        "isLoop": false,
        "isAssign": false,
        "prefix": false,
        "postfix": false,
        "binop": null,
        "updateContext": null
      },
      "start": 149,
      "end": 150,
      "loc": {
        "start": {
          "line": 5,
          "column": 33
        },
        "end": {
          "line": 5,
          "column": 34
        }
      }
    },
    {
      "type": {
        "label": "name",
        "beforeExpr": false,
        "startsExpr": true,
        "rightAssociative": false,
        "isLoop": false,
        "isAssign": false,
        "prefix": false,
        "postfix": false,
        "binop": null
      },
      "value": "Vec3",
      "start": 151,
      "end": 155,
      "loc": {
        "start": {
          "line": 5,
          "column": 35
        },
        "end": {
          "line": 5,
          "column": 39
        }
      }
    },
    {
      "type": {
        "label": ",",
        "beforeExpr": true,
        "startsExpr": false,
        "rightAssociative": false,
        "isLoop": false,
        "isAssign": false,
        "prefix": false,
        "postfix": false,
        "binop": null,
        "updateContext": null
      },
      "start": 155,
      "end": 156,
      "loc": {
        "start": {
          "line": 5,
          "column": 39
        },
        "end": {
          "line": 5,
          "column": 40
        }
      }
    },
    {
      "type": {
        "label": "name",
        "beforeExpr": false,
        "startsExpr": true,
        "rightAssociative": false,
        "isLoop": false,
        "isAssign": false,
        "prefix": false,
        "postfix": false,
        "binop": null
      },
      "value": "Mat4",
      "start": 157,
      "end": 161,
      "loc": {
        "start": {
          "line": 5,
          "column": 41
        },
        "end": {
          "line": 5,
          "column": 45
        }
      }
    },
    {
      "type": {
        "label": "}",
        "beforeExpr": false,
        "startsExpr": false,
        "rightAssociative": false,
        "isLoop": false,
        "isAssign": false,
        "prefix": false,
        "postfix": false,
        "binop": null
      },
      "start": 162,
      "end": 163,
      "loc": {
        "start": {
          "line": 5,
          "column": 46
        },
        "end": {
          "line": 5,
          "column": 47
        }
      }
    },
    {
      "type": {
        "label": ";",
        "beforeExpr": true,
        "startsExpr": false,
        "rightAssociative": false,
        "isLoop": false,
        "isAssign": false,
        "prefix": false,
        "postfix": false,
        "binop": null,
        "updateContext": null
      },
      "start": 163,
      "end": 164,
      "loc": {
        "start": {
          "line": 5,
          "column": 47
        },
        "end": {
          "line": 5,
          "column": 48
        }
      }
    },
    {
      "type": {
        "label": "eof",
        "beforeExpr": false,
        "startsExpr": false,
        "rightAssociative": false,
        "isLoop": false,
        "isAssign": false,
        "prefix": false,
        "postfix": false,
        "binop": null,
        "updateContext": null
      },
      "start": 165,
      "end": 165,
      "loc": {
        "start": {
          "line": 6,
          "column": 0
        },
        "end": {
          "line": 6,
          "column": 0
        }
      }
    }
  ]
}